[
  {
    "kpi_categorie_juridique": [
      {
        "code_cat_juridique": "10", 
        "libelle_cat_juridique": "Entrepreneur individuel", 
        "montant": "86191337.53", 
        "nombre": "54730", 
        "nombre_siren": "12128"
      }, 
      {
        "code_cat_juridique": "54", 
        "libelle_cat_juridique": "Soci\u00e9t\u00e9 \u00e0 responsabilit\u00e9 limit\u00e9e (SARL)", 
        "montant": "33175687.31", 
        "nombre": "13080", 
        "nombre_siren": "3199"
      }, 
      {
        "code_cat_juridique": "57", 
        "libelle_cat_juridique": "Soci\u00e9t\u00e9 par actions simplifi\u00e9e", 
        "montant": "26176378.67", 
        "nombre": "12283", 
        "nombre_siren": "2735"
      }, 
      {
        "code_cat_juridique": "Autres", 
        "libelle_cat_juridique": "Autres Cat\u00e9gories Juridiques", 
        "montant": "3266716.85", 
        "nombre": "1664", 
        "nombre_siren": "415"
      }
    ], 
    "kpi_classe_effectif": [
      {
        "classe_effectif": "00", 
        "libelle_classe_effectif": "0 salari\u00e9", 
        "montant": "6352233.28", 
        "nombre": "3244", 
        "nombre_siren": "777"
      }, 
      {
        "classe_effectif": "01", 
        "libelle_classe_effectif": "1 ou 2 salari\u00e9s", 
        "montant": "22456562.75", 
        "nombre": "10690", 
        "nombre_siren": "2754"
      }, 
      {
        "classe_effectif": "02", 
        "libelle_classe_effectif": "3 \u00e0 5 salari\u00e9s", 
        "montant": "9432604.78", 
        "nombre": "3613", 
        "nombre_siren": "1004"
      }, 
      {
        "classe_effectif": "03", 
        "libelle_classe_effectif": "6 \u00e0 9 salari\u00e9s", 
        "montant": "4423166.40", 
        "nombre": "1206", 
        "nombre_siren": "363"
      }, 
      {
        "classe_effectif": "NN", 
        "libelle_classe_effectif": "Etablissement non employeur", 
        "montant": "18786120.00", 
        "nombre": "11760", 
        "nombre_siren": "2610"
      }, 
      {
        "classe_effectif": "Autres", 
        "libelle_classe_effectif": "Autres Classes d'Effectifs", 
        "montant": "4808688.00", 
        "nombre": "481", 
        "nombre_siren": "134"
      }
    ], 
    "kpi_top_10_naf": [
      {
        "libelle_section_naf": "H\u00e9bergement et restauration", 
        "montant": "30301093.53", 
        "nombre": "13586", 
        "nombre_siren": "2034", 
        "section_naf": "I"
      }, 
      {
        "libelle_section_naf": "Agriculture, sylviculture et p\u00eache", 
        "montant": "20669710.95", 
        "nombre": "12996", 
        "nombre_siren": "2553", 
        "section_naf": "A"
      }, 
      {
        "libelle_section_naf": "Commerce", 
        "montant": "20913293.17", 
        "nombre": "12379", 
        "nombre_siren": "3128", 
        "section_naf": "G"
      }, 
      {
        "libelle_section_naf": "Activit\u00e9s de services administratifs et de soutien", 
        "montant": "16086498.04", 
        "nombre": "7151", 
        "nombre_siren": "1371", 
        "section_naf": "N"
      }, 
      {
        "libelle_section_naf": "Construction", 
        "montant": "10268454.71", 
        "nombre": "6600", 
        "nombre_siren": "2152", 
        "section_naf": "F"
      }, 
      {
        "libelle_section_naf": "Activit\u00e9s sp\u00e9cialis\u00e9es, scientifiques et techniques", 
        "montant": "8175910.50", 
        "nombre": "4677", 
        "nombre_siren": "1251", 
        "section_naf": "M"
      }, 
      {
        "libelle_section_naf": "Industrie manufacturi\u00e8re", 
        "montant": "8149965.95", 
        "nombre": "4630", 
        "nombre_siren": "1186", 
        "section_naf": "C"
      }, 
      {
        "libelle_section_naf": "Autres activit\u00e9s de services", 
        "montant": "5964759.85", 
        "nombre": "4135", 
        "nombre_siren": "1120", 
        "section_naf": "S"
      }, 
      {
        "libelle_section_naf": "Transports et entreposage", 
        "montant": "7320727.00", 
        "nombre": "3917", 
        "nombre_siren": "728", 
        "section_naf": "H"
      }, 
      {
        "libelle_section_naf": "Arts, spectacles et activit\u00e9s r\u00e9cr\u00e9atives", 
        "montant": "7128494.94", 
        "nombre": "3117", 
        "nombre_siren": "479", 
        "section_naf": "R"
      }, 
      {
        "libelle_section_naf": "Autres sections NAF", 
        "montant": "14067589.72", 
        "nombre": "8775", 
        "nombre_siren": "2536", 
        "section_naf": "Autres"
      }
    ], 
    "libelle": "Guadeloupe", 
    "montant": "149046498.36", 
    "nombre": "81963", 
    "nombre_siren": "18510", 
    "reg": "01"
  }, 
  {
    "kpi_categorie_juridique": [
      {
        "code_cat_juridique": "10", 
        "libelle_cat_juridique": "Entrepreneur individuel", 
        "montant": "46561410.00", 
        "nombre": "29833", 
        "nombre_siren": "7059"
      }, 
      {
        "code_cat_juridique": "54", 
        "libelle_cat_juridique": "Soci\u00e9t\u00e9 \u00e0 responsabilit\u00e9 limit\u00e9e (SARL)", 
        "montant": "34562929.81", 
        "nombre": "12583", 
        "nombre_siren": "3162"
      }, 
      {
        "code_cat_juridique": "57", 
        "libelle_cat_juridique": "Soci\u00e9t\u00e9 par actions simplifi\u00e9e", 
        "montant": "21583157.35", 
        "nombre": "8979", 
        "nombre_siren": "2060"
      }, 
      {
        "code_cat_juridique": "Autres", 
        "libelle_cat_juridique": "Autres Cat\u00e9gories Juridiques", 
        "montant": "2743724.00", 
        "nombre": "1090", 
        "nombre_siren": "287"
      }
    ], 
    "kpi_classe_effectif": [
      {
        "classe_effectif": "00", 
        "libelle_classe_effectif": "0 salari\u00e9", 
        "montant": "6098082.00", 
        "nombre": "2783", 
        "nombre_siren": "686"
      }, 
      {
        "classe_effectif": "01", 
        "libelle_classe_effectif": "1 ou 2 salari\u00e9s", 
        "montant": "21382017.34", 
        "nombre": "8779", 
        "nombre_siren": "2218"
      }, 
      {
        "classe_effectif": "02", 
        "libelle_classe_effectif": "3 \u00e0 5 salari\u00e9s", 
        "montant": "9596508.60", 
        "nombre": "3141", 
        "nombre_siren": "941"
      }, 
      {
        "classe_effectif": "03", 
        "libelle_classe_effectif": "6 \u00e0 9 salari\u00e9s", 
        "montant": "4243817.00", 
        "nombre": "1186", 
        "nombre_siren": "361"
      }, 
      {
        "classe_effectif": "NN", 
        "libelle_classe_effectif": "Etablissement non employeur", 
        "montant": "9163535.00", 
        "nombre": "5984", 
        "nombre_siren": "1406"
      }, 
      {
        "classe_effectif": "Autres", 
        "libelle_classe_effectif": "Autres Classes d'Effectifs", 
        "montant": "5345829.00", 
        "nombre": "583", 
        "nombre_siren": "191"
      }
    ], 
    "kpi_top_10_naf": [
      {
        "libelle_section_naf": "Commerce", 
        "montant": "18269705.00", 
        "nombre": "9090", 
        "nombre_siren": "2192", 
        "section_naf": "G"
      }, 
      {
        "libelle_section_naf": "H\u00e9bergement et restauration", 
        "montant": "20801999.34", 
        "nombre": "7117", 
        "nombre_siren": "1247", 
        "section_naf": "I"
      }, 
      {
        "libelle_section_naf": "Autres activit\u00e9s de services", 
        "montant": "7729418.00", 
        "nombre": "4622", 
        "nombre_siren": "1058", 
        "section_naf": "S"
      }, 
      {
        "libelle_section_naf": "Activit\u00e9s de services administratifs et de soutien", 
        "montant": "9980408.60", 
        "nombre": "4551", 
        "nombre_siren": "924", 
        "section_naf": "N"
      }, 
      {
        "libelle_section_naf": "Activit\u00e9s sp\u00e9cialis\u00e9es, scientifiques et techniques", 
        "montant": "7787469.00", 
        "nombre": "4097", 
        "nombre_siren": "1094", 
        "section_naf": "M"
      }, 
      {
        "libelle_section_naf": "Construction", 
        "montant": "6642125.00", 
        "nombre": "4083", 
        "nombre_siren": "1375", 
        "section_naf": "F"
      }, 
      {
        "libelle_section_naf": "Transports et entreposage", 
        "montant": "7599327.22", 
        "nombre": "3505", 
        "nombre_siren": "710", 
        "section_naf": "H"
      }, 
      {
        "libelle_section_naf": "Agriculture, sylviculture et p\u00eache", 
        "montant": "4460155.00", 
        "nombre": "3185", 
        "nombre_siren": "768", 
        "section_naf": "A"
      }, 
      {
        "libelle_section_naf": "Industrie manufacturi\u00e8re", 
        "montant": "5463252.00", 
        "nombre": "3160", 
        "nombre_siren": "822", 
        "section_naf": "C"
      }, 
      {
        "libelle_section_naf": "Arts, spectacles et activit\u00e9s r\u00e9cr\u00e9atives", 
        "montant": "5334273.00", 
        "nombre": "2310", 
        "nombre_siren": "370", 
        "section_naf": "R"
      }, 
      {
        "libelle_section_naf": "Autres sections NAF", 
        "montant": "11676464.00", 
        "nombre": "7016", 
        "nombre_siren": "2055", 
        "section_naf": "Autres"
      }
    ], 
    "libelle": "Martinique", 
    "montant": "105744596.16", 
    "nombre": "52736", 
    "nombre_siren": "12595", 
    "reg": "02"
  }, 
  {
    "kpi_categorie_juridique": [
      {
        "code_cat_juridique": "10", 
        "libelle_cat_juridique": "Entrepreneur individuel", 
        "montant": "46470445.17", 
        "nombre": "22449", 
        "nombre_siren": "3665"
      }, 
      {
        "code_cat_juridique": "57", 
        "libelle_cat_juridique": "Soci\u00e9t\u00e9 par actions simplifi\u00e9e", 
        "montant": "17973752.02", 
        "nombre": "7249", 
        "nombre_siren": "1231"
      }, 
      {
        "code_cat_juridique": "54", 
        "libelle_cat_juridique": "Soci\u00e9t\u00e9 \u00e0 responsabilit\u00e9 limit\u00e9e (SARL)", 
        "montant": "13495582.38", 
        "nombre": "4997", 
        "nombre_siren": "889"
      }, 
      {
        "code_cat_juridique": "Autres", 
        "libelle_cat_juridique": "Autres Cat\u00e9gories Juridiques", 
        "montant": "1684059.23", 
        "nombre": "765", 
        "nombre_siren": "143"
      }
    ], 
    "kpi_classe_effectif": [
      {
        "classe_effectif": "00", 
        "libelle_classe_effectif": "0 salari\u00e9", 
        "montant": "5066499.77", 
        "nombre": "2140", 
        "nombre_siren": "371"
      }, 
      {
        "classe_effectif": "01", 
        "libelle_classe_effectif": "1 ou 2 salari\u00e9s", 
        "montant": "12412670.56", 
        "nombre": "5141", 
        "nombre_siren": "945"
      }, 
      {
        "classe_effectif": "02", 
        "libelle_classe_effectif": "3 \u00e0 5 salari\u00e9s", 
        "montant": "5735934.00", 
        "nombre": "2053", 
        "nombre_siren": "405"
      }, 
      {
        "classe_effectif": "03", 
        "libelle_classe_effectif": "6 \u00e0 9 salari\u00e9s", 
        "montant": "2222790.00", 
        "nombre": "683", 
        "nombre_siren": "141"
      }, 
      {
        "classe_effectif": "NN", 
        "libelle_classe_effectif": "Etablissement non employeur", 
        "montant": "6757612.00", 
        "nombre": "3404", 
        "nombre_siren": "552"
      }, 
      {
        "classe_effectif": "Autres", 
        "libelle_classe_effectif": "Autres Classes d'Effectifs", 
        "montant": "1542828.69", 
        "nombre": "318", 
        "nombre_siren": "68"
      }
    ], 
    "kpi_top_10_naf": [
      {
        "libelle_section_naf": "Construction", 
        "montant": "14442062.00", 
        "nombre": "6325", 
        "nombre_siren": "1070", 
        "section_naf": "F"
      }, 
      {
        "libelle_section_naf": "Agriculture, sylviculture et p\u00eache", 
        "montant": "9318728.00", 
        "nombre": "5395", 
        "nombre_siren": "807", 
        "section_naf": "A"
      }, 
      {
        "libelle_section_naf": "Commerce", 
        "montant": "11446073.84", 
        "nombre": "5241", 
        "nombre_siren": "959", 
        "section_naf": "G"
      }, 
      {
        "libelle_section_naf": "H\u00e9bergement et restauration", 
        "montant": "11358024.74", 
        "nombre": "4061", 
        "nombre_siren": "568", 
        "section_naf": "I"
      }, 
      {
        "libelle_section_naf": "Activit\u00e9s de services administratifs et de soutien", 
        "montant": "6551883.40", 
        "nombre": "2538", 
        "nombre_siren": "387", 
        "section_naf": "N"
      }, 
      {
        "libelle_section_naf": "Industrie manufacturi\u00e8re", 
        "montant": "4764633.84", 
        "nombre": "2233", 
        "nombre_siren": "395", 
        "section_naf": "C"
      }, 
      {
        "libelle_section_naf": "Activit\u00e9s sp\u00e9cialis\u00e9es, scientifiques et techniques", 
        "montant": "4977872.00", 
        "nombre": "2222", 
        "nombre_siren": "420", 
        "section_naf": "M"
      }, 
      {
        "libelle_section_naf": "Transports et entreposage", 
        "montant": "4465183.60", 
        "nombre": "1769", 
        "nombre_siren": "288", 
        "section_naf": "H"
      }, 
      {
        "libelle_section_naf": "Autres activit\u00e9s de services", 
        "montant": "3255018.00", 
        "nombre": "1639", 
        "nombre_siren": "279", 
        "section_naf": "S"
      }, 
      {
        "libelle_section_naf": "Arts, spectacles et activit\u00e9s r\u00e9cr\u00e9atives", 
        "montant": "2463400.87", 
        "nombre": "935", 
        "nombre_siren": "134", 
        "section_naf": "R"
      }, 
      {
        "libelle_section_naf": "Autres sections NAF", 
        "montant": "6627929.51", 
        "nombre": "3138", 
        "nombre_siren": "634", 
        "section_naf": "Autres"
      }
    ], 
    "libelle": "Guyane", 
    "montant": "79670809.80", 
    "nombre": "35496", 
    "nombre_siren": "5931", 
    "reg": "03"
  }, 
  {
    "kpi_categorie_juridique": [
      {
        "code_cat_juridique": "10", 
        "libelle_cat_juridique": "Entrepreneur individuel", 
        "montant": "94620520.29", 
        "nombre": "64370", 
        "nombre_siren": "17337"
      }, 
      {
        "code_cat_juridique": "54", 
        "libelle_cat_juridique": "Soci\u00e9t\u00e9 \u00e0 responsabilit\u00e9 limit\u00e9e (SARL)", 
        "montant": "46525120.09", 
        "nombre": "19283", 
        "nombre_siren": "5994"
      }, 
      {
        "code_cat_juridique": "57", 
        "libelle_cat_juridique": "Soci\u00e9t\u00e9 par actions simplifi\u00e9e", 
        "montant": "13789106.00", 
        "nombre": "5511", 
        "nombre_siren": "1576"
      }, 
      {
        "code_cat_juridique": "Autres", 
        "libelle_cat_juridique": "Autres Cat\u00e9gories Juridiques", 
        "montant": "4586949.75", 
        "nombre": "1836", 
        "nombre_siren": "542"
      }
    ], 
    "kpi_classe_effectif": [
      {
        "classe_effectif": "00", 
        "libelle_classe_effectif": "0 salari\u00e9", 
        "montant": "12279326.91", 
        "nombre": "6715", 
        "nombre_siren": "1893"
      }, 
      {
        "classe_effectif": "01", 
        "libelle_classe_effectif": "1 ou 2 salari\u00e9s", 
        "montant": "29699854.38", 
        "nombre": "15431", 
        "nombre_siren": "4954"
      }, 
      {
        "classe_effectif": "02", 
        "libelle_classe_effectif": "3 \u00e0 5 salari\u00e9s", 
        "montant": "11683259.21", 
        "nombre": "4969", 
        "nombre_siren": "1855"
      }, 
      {
        "classe_effectif": "03", 
        "libelle_classe_effectif": "6 \u00e0 9 salari\u00e9s", 
        "montant": "6808506.88", 
        "nombre": "1849", 
        "nombre_siren": "710"
      }, 
      {
        "classe_effectif": "NN", 
        "libelle_classe_effectif": "Etablissement non employeur", 
        "montant": "10617114.00", 
        "nombre": "7403", 
        "nombre_siren": "2063"
      }, 
      {
        "classe_effectif": "Autres", 
        "libelle_classe_effectif": "Autres Classes d'Effectifs", 
        "montant": "9810278.00", 
        "nombre": "788", 
        "nombre_siren": "247"
      }
    ], 
    "kpi_top_10_naf": [
      {
        "libelle_section_naf": "Commerce", 
        "montant": "28719838.00", 
        "nombre": "18090", 
        "nombre_siren": "5136", 
        "section_naf": "G"
      }, 
      {
        "libelle_section_naf": "H\u00e9bergement et restauration", 
        "montant": "30183284.47", 
        "nombre": "13498", 
        "nombre_siren": "2455", 
        "section_naf": "I"
      }, 
      {
        "libelle_section_naf": "Construction", 
        "montant": "12972148.91", 
        "nombre": "8625", 
        "nombre_siren": "3225", 
        "section_naf": "F"
      }, 
      {
        "libelle_section_naf": "Agriculture, sylviculture et p\u00eache", 
        "montant": "9669144.00", 
        "nombre": "6858", 
        "nombre_siren": "1759", 
        "section_naf": "A"
      }, 
      {
        "libelle_section_naf": "Autres activit\u00e9s de services", 
        "montant": "8378700.55", 
        "nombre": "6293", 
        "nombre_siren": "1970", 
        "section_naf": "S"
      }, 
      {
        "libelle_section_naf": "Activit\u00e9s sp\u00e9cialis\u00e9es, scientifiques et techniques", 
        "montant": "10820694.00", 
        "nombre": "6040", 
        "nombre_siren": "1812", 
        "section_naf": "M"
      }, 
      {
        "libelle_section_naf": "Sant\u00e9 humaine et action sociale", 
        "montant": "7940078.00", 
        "nombre": "5614", 
        "nombre_siren": "2467", 
        "section_naf": "Q"
      }, 
      {
        "libelle_section_naf": "Industrie manufacturi\u00e8re", 
        "montant": "8603973.00", 
        "nombre": "5431", 
        "nombre_siren": "1637", 
        "section_naf": "C"
      }, 
      {
        "libelle_section_naf": "Arts, spectacles et activit\u00e9s r\u00e9cr\u00e9atives", 
        "montant": "11190566.00", 
        "nombre": "5285", 
        "nombre_siren": "881", 
        "section_naf": "R"
      }, 
      {
        "libelle_section_naf": "Enseignement", 
        "montant": "6709659.20", 
        "nombre": "4895", 
        "nombre_siren": "1236", 
        "section_naf": "P"
      }, 
      {
        "libelle_section_naf": "Autres sections NAF", 
        "montant": "25470699.00", 
        "nombre": "11284", 
        "nombre_siren": "3023", 
        "section_naf": "Autres"
      }
    ], 
    "libelle": "La R\u00e9union", 
    "montant": "160658785.13", 
    "nombre": "91913", 
    "nombre_siren": "25554", 
    "reg": "04"
  }, 
  {
    "kpi_categorie_juridique": [
      {
        "code_cat_juridique": "10", 
        "libelle_cat_juridique": "Entrepreneur individuel", 
        "montant": "96386476.00", 
        "nombre": "40108", 
        "nombre_siren": "5396"
      }, 
      {
        "code_cat_juridique": "54", 
        "libelle_cat_juridique": "Soci\u00e9t\u00e9 \u00e0 responsabilit\u00e9 limit\u00e9e (SARL)", 
        "montant": "10602978.23", 
        "nombre": "3850", 
        "nombre_siren": "677"
      }, 
      {
        "code_cat_juridique": "57", 
        "libelle_cat_juridique": "Soci\u00e9t\u00e9 par actions simplifi\u00e9e", 
        "montant": "1307805.00", 
        "nombre": "518", 
        "nombre_siren": "92"
      }, 
      {
        "code_cat_juridique": "Autres", 
        "libelle_cat_juridique": "Autres Cat\u00e9gories Juridiques", 
        "montant": "921662.00", 
        "nombre": "371", 
        "nombre_siren": "60"
      }
    ], 
    "kpi_classe_effectif": [
      {
        "classe_effectif": "00", 
        "libelle_classe_effectif": "0 salari\u00e9", 
        "montant": "3647841.00", 
        "nombre": "1247", 
        "nombre_siren": "239"
      }, 
      {
        "classe_effectif": "01", 
        "libelle_classe_effectif": "1 ou 2 salari\u00e9s", 
        "montant": "2417924.00", 
        "nombre": "870", 
        "nombre_siren": "137"
      }, 
      {
        "classe_effectif": "02", 
        "libelle_classe_effectif": "3 \u00e0 5 salari\u00e9s", 
        "montant": "898081.00", 
        "nombre": "313", 
        "nombre_siren": "63"
      }, 
      {
        "classe_effectif": "03", 
        "libelle_classe_effectif": "6 \u00e0 9 salari\u00e9s", 
        "montant": "228865.00", 
        "nombre": "85", 
        "nombre_siren": "23"
      }, 
      {
        "classe_effectif": "Autres", 
        "libelle_classe_effectif": "Autres Classes d'Effectifs", 
        "montant": "359855.00", 
        "nombre": "71", 
        "nombre_siren": "13"
      }
    ], 
    "kpi_top_10_naf": [
      {
        "libelle_section_naf": "Commerce", 
        "montant": "49329534.84", 
        "nombre": "20567", 
        "nombre_siren": "2781", 
        "section_naf": "G"
      }, 
      {
        "libelle_section_naf": "Agriculture, sylviculture et p\u00eache", 
        "montant": "18477135.00", 
        "nombre": "8183", 
        "nombre_siren": "1084", 
        "section_naf": "A"
      }, 
      {
        "libelle_section_naf": "Construction", 
        "montant": "11361400.00", 
        "nombre": "4541", 
        "nombre_siren": "676", 
        "section_naf": "F"
      }, 
      {
        "libelle_section_naf": "Transports et entreposage", 
        "montant": "11012709.00", 
        "nombre": "4117", 
        "nombre_siren": "521", 
        "section_naf": "H"
      }, 
      {
        "libelle_section_naf": "H\u00e9bergement et restauration", 
        "montant": "6347737.05", 
        "nombre": "2252", 
        "nombre_siren": "315", 
        "section_naf": "I"
      }, 
      {
        "libelle_section_naf": "Industrie manufacturi\u00e8re", 
        "montant": "3427463.00", 
        "nombre": "1385", 
        "nombre_siren": "202", 
        "section_naf": "C"
      }, 
      {
        "libelle_section_naf": "Activit\u00e9s de services administratifs et de soutien", 
        "montant": "2217466.00", 
        "nombre": "834", 
        "nombre_siren": "122", 
        "section_naf": "N"
      }, 
      {
        "libelle_section_naf": "Autres activit\u00e9s de services", 
        "montant": "1572705.00", 
        "nombre": "706", 
        "nombre_siren": "112", 
        "section_naf": "S"
      }, 
      {
        "libelle_section_naf": "Activit\u00e9s sp\u00e9cialis\u00e9es, scientifiques et techniques", 
        "montant": "1525784.00", 
        "nombre": "693", 
        "nombre_siren": "129", 
        "section_naf": "M"
      }, 
      {
        "libelle_section_naf": "Enseignement", 
        "montant": "1279783.00", 
        "nombre": "517", 
        "nombre_siren": "74", 
        "section_naf": "P"
      }, 
      {
        "libelle_section_naf": "Autres sections NAF", 
        "montant": "2788374.34", 
        "nombre": "1136", 
        "nombre_siren": "218", 
        "section_naf": "Autres"
      }
    ], 
    "libelle": "Mayotte", 
    "montant": "109340091.23", 
    "nombre": "44931", 
    "nombre_siren": "6226", 
    "reg": "06"
  }, 
  {
    "kpi_categorie_juridique": [
      {
        "code_cat_juridique": "54", 
        "libelle_cat_juridique": "Soci\u00e9t\u00e9 \u00e0 responsabilit\u00e9 limit\u00e9e (SARL)", 
        "montant": "2068640286.45", 
        "nombre": "481547", 
        "nombre_siren": "103444"
      }, 
      {
        "code_cat_juridique": "57", 
        "libelle_cat_juridique": "Soci\u00e9t\u00e9 par actions simplifi\u00e9e", 
        "montant": "1912719294.20", 
        "nombre": "445495", 
        "nombre_siren": "88672"
      }, 
      {
        "code_cat_juridique": "10", 
        "libelle_cat_juridique": "Entrepreneur individuel", 
        "montant": "1874794032.27", 
        "nombre": "1075242", 
        "nombre_siren": "218314"
      }, 
      {
        "code_cat_juridique": "Autres", 
        "libelle_cat_juridique": "Autres Cat\u00e9gories Juridiques", 
        "montant": "211645452.97", 
        "nombre": "34443", 
        "nombre_siren": "7870"
      }
    ], 
    "kpi_classe_effectif": [
      {
        "classe_effectif": "00", 
        "libelle_classe_effectif": "0 salari\u00e9", 
        "montant": "330486368.28", 
        "nombre": "117820", 
        "nombre_siren": "24497"
      }, 
      {
        "classe_effectif": "01", 
        "libelle_classe_effectif": "1 ou 2 salari\u00e9s", 
        "montant": "1072348403.24", 
        "nombre": "320894", 
        "nombre_siren": "70178"
      }, 
      {
        "classe_effectif": "02", 
        "libelle_classe_effectif": "3 \u00e0 5 salari\u00e9s", 
        "montant": "798101770.84", 
        "nombre": "157127", 
        "nombre_siren": "33802"
      }, 
      {
        "classe_effectif": "03", 
        "libelle_classe_effectif": "6 \u00e0 9 salari\u00e9s", 
        "montant": "486984920.87", 
        "nombre": "65193", 
        "nombre_siren": "13497"
      }, 
      {
        "classe_effectif": "NN", 
        "libelle_classe_effectif": "Etablissement non employeur", 
        "montant": "202446528.94", 
        "nombre": "107440", 
        "nombre_siren": "22585"
      }, 
      {
        "classe_effectif": "Autres", 
        "libelle_classe_effectif": "Autres Classes d'Effectifs", 
        "montant": "923970366.38", 
        "nombre": "41577", 
        "nombre_siren": "9718"
      }
    ], 
    "kpi_top_10_naf": [
      {
        "libelle_section_naf": "Transports et entreposage", 
        "montant": "998138861.16", 
        "nombre": "450444", 
        "nombre_siren": "60243", 
        "section_naf": "H"
      }, 
      {
        "libelle_section_naf": "Activit\u00e9s sp\u00e9cialis\u00e9es, scientifiques et techniques", 
        "montant": "664858035.03", 
        "nombre": "287158", 
        "nombre_siren": "68337", 
        "section_naf": "M"
      }, 
      {
        "libelle_section_naf": "H\u00e9bergement et restauration", 
        "montant": "1743429023.19", 
        "nombre": "263130", 
        "nombre_siren": "37194", 
        "section_naf": "I"
      }, 
      {
        "libelle_section_naf": "Commerce", 
        "montant": "654518311.45", 
        "nombre": "228452", 
        "nombre_siren": "56818", 
        "section_naf": "G"
      }, 
      {
        "libelle_section_naf": "Arts, spectacles et activit\u00e9s r\u00e9cr\u00e9atives", 
        "montant": "499309308.63", 
        "nombre": "176600", 
        "nombre_siren": "28475", 
        "section_naf": "R"
      }, 
      {
        "libelle_section_naf": "Autres activit\u00e9s de services", 
        "montant": "243117890.58", 
        "nombre": "116286", 
        "nombre_siren": "28472", 
        "section_naf": "S"
      }, 
      {
        "libelle_section_naf": "Activit\u00e9s de services administratifs et de soutien", 
        "montant": "387899353.22", 
        "nombre": "93908", 
        "nombre_siren": "17436", 
        "section_naf": "N"
      }, 
      {
        "libelle_section_naf": "Construction", 
        "montant": "163028947.21", 
        "nombre": "93367", 
        "nombre_siren": "31931", 
        "section_naf": "F"
      }, 
      {
        "libelle_section_naf": "Information et communication", 
        "montant": "257269800.33", 
        "nombre": "89335", 
        "nombre_siren": "19774", 
        "section_naf": "J"
      }, 
      {
        "libelle_section_naf": "Enseignement", 
        "montant": "134369572.73", 
        "nombre": "79371", 
        "nombre_siren": "16279", 
        "section_naf": "P"
      }, 
      {
        "libelle_section_naf": "Autres sections NAF", 
        "montant": "346238808.36", 
        "nombre": "178779", 
        "nombre_siren": "56458", 
        "section_naf": "Autres"
      }
    ], 
    "libelle": "\u00cele-de-France", 
    "montant": "6092177911.89", 
    "nombre": "2056830", 
    "nombre_siren": "420071", 
    "reg": "11"
  }, 
  {
    "kpi_categorie_juridique": [
      {
        "code_cat_juridique": "54", 
        "libelle_cat_juridique": "Soci\u00e9t\u00e9 \u00e0 responsabilit\u00e9 limit\u00e9e (SARL)", 
        "montant": "246783542.52", 
        "nombre": "59911", 
        "nombre_siren": "14761"
      }, 
      {
        "code_cat_juridique": "10", 
        "libelle_cat_juridique": "Entrepreneur individuel", 
        "montant": "221773861.09", 
        "nombre": "126371", 
        "nombre_siren": "33258"
      }, 
      {
        "code_cat_juridique": "57", 
        "libelle_cat_juridique": "Soci\u00e9t\u00e9 par actions simplifi\u00e9e", 
        "montant": "105980327.95", 
        "nombre": "24964", 
        "nombre_siren": "5900"
      }, 
      {
        "code_cat_juridique": "Autres", 
        "libelle_cat_juridique": "Autres Cat\u00e9gories Juridiques", 
        "montant": "35880383.25", 
        "nombre": "8864", 
        "nombre_siren": "2227"
      }
    ], 
    "kpi_classe_effectif": [
      {
        "classe_effectif": "00", 
        "libelle_classe_effectif": "0 salari\u00e9", 
        "montant": "45317630.00", 
        "nombre": "15617", 
        "nombre_siren": "3757"
      }, 
      {
        "classe_effectif": "01", 
        "libelle_classe_effectif": "1 ou 2 salari\u00e9s", 
        "montant": "162771772.61", 
        "nombre": "46093", 
        "nombre_siren": "11598"
      }, 
      {
        "classe_effectif": "02", 
        "libelle_classe_effectif": "3 \u00e0 5 salari\u00e9s", 
        "montant": "88144369.75", 
        "nombre": "17972", 
        "nombre_siren": "4599"
      }, 
      {
        "classe_effectif": "03", 
        "libelle_classe_effectif": "6 \u00e0 9 salari\u00e9s", 
        "montant": "37193803.26", 
        "nombre": "5455", 
        "nombre_siren": "1400"
      }, 
      {
        "classe_effectif": "NN", 
        "libelle_classe_effectif": "Etablissement non employeur", 
        "montant": "28006511.00", 
        "nombre": "15111", 
        "nombre_siren": "3938"
      }, 
      {
        "classe_effectif": "Autres", 
        "libelle_classe_effectif": "Autres Classes d'Effectifs", 
        "montant": "55492694.00", 
        "nombre": "3104", 
        "nombre_siren": "803"
      }
    ], 
    "kpi_top_10_naf": [
      {
        "libelle_section_naf": "H\u00e9bergement et restauration", 
        "montant": "233487092.28", 
        "nombre": "45600", 
        "nombre_siren": "6525", 
        "section_naf": "I"
      }, 
      {
        "libelle_section_naf": "Commerce", 
        "montant": "78682801.33", 
        "nombre": "34002", 
        "nombre_siren": "9769", 
        "section_naf": "G"
      }, 
      {
        "libelle_section_naf": "Autres activit\u00e9s de services", 
        "montant": "44168631.00", 
        "nombre": "24131", 
        "nombre_siren": "6588", 
        "section_naf": "S"
      }, 
      {
        "libelle_section_naf": "Construction", 
        "montant": "29581682.26", 
        "nombre": "18977", 
        "nombre_siren": "7696", 
        "section_naf": "F"
      }, 
      {
        "libelle_section_naf": "Arts, spectacles et activit\u00e9s r\u00e9cr\u00e9atives", 
        "montant": "52568790.91", 
        "nombre": "18288", 
        "nombre_siren": "3034", 
        "section_naf": "R"
      }, 
      {
        "libelle_section_naf": "Activit\u00e9s sp\u00e9cialis\u00e9es, scientifiques et techniques", 
        "montant": "43769472.00", 
        "nombre": "16826", 
        "nombre_siren": "4419", 
        "section_naf": "M"
      }, 
      {
        "libelle_section_naf": "Sant\u00e9 humaine et action sociale", 
        "montant": "14008411.00", 
        "nombre": "10663", 
        "nombre_siren": "4517", 
        "section_naf": "Q"
      }, 
      {
        "libelle_section_naf": "Enseignement", 
        "montant": "18915391.00", 
        "nombre": "10440", 
        "nombre_siren": "2274", 
        "section_naf": "P"
      }, 
      {
        "libelle_section_naf": "Activit\u00e9s de services administratifs et de soutien", 
        "montant": "23539780.00", 
        "nombre": "8871", 
        "nombre_siren": "2277", 
        "section_naf": "N"
      }, 
      {
        "libelle_section_naf": "Industrie manufacturi\u00e8re", 
        "montant": "15568198.03", 
        "nombre": "8865", 
        "nombre_siren": "2643", 
        "section_naf": "C"
      }, 
      {
        "libelle_section_naf": "Autres sections NAF", 
        "montant": "58961625.00", 
        "nombre": "25959", 
        "nombre_siren": "6834", 
        "section_naf": "Autres"
      }
    ], 
    "libelle": "Centre-Val de Loire", 
    "montant": "613251874.81", 
    "nombre": "222622", 
    "nombre_siren": "56453", 
    "reg": "24"
  }, 
  {
    "kpi_categorie_juridique": [
      {
        "code_cat_juridique": "54", 
        "libelle_cat_juridique": "Soci\u00e9t\u00e9 \u00e0 responsabilit\u00e9 limit\u00e9e (SARL)", 
        "montant": "303015957.95", 
        "nombre": "71125", 
        "nombre_siren": "17374"
      }, 
      {
        "code_cat_juridique": "10", 
        "libelle_cat_juridique": "Entrepreneur individuel", 
        "montant": "254346891.48", 
        "nombre": "145930", 
        "nombre_siren": "37716"
      }, 
      {
        "code_cat_juridique": "57", 
        "libelle_cat_juridique": "Soci\u00e9t\u00e9 par actions simplifi\u00e9e", 
        "montant": "126030544.53", 
        "nombre": "27447", 
        "nombre_siren": "6408"
      }, 
      {
        "code_cat_juridique": "Autres", 
        "libelle_cat_juridique": "Autres Cat\u00e9gories Juridiques", 
        "montant": "40840700.69", 
        "nombre": "10059", 
        "nombre_siren": "2627"
      }
    ], 
    "kpi_classe_effectif": [
      {
        "classe_effectif": "00", 
        "libelle_classe_effectif": "0 salari\u00e9", 
        "montant": "58186621.82", 
        "nombre": "20034", 
        "nombre_siren": "4790"
      }, 
      {
        "classe_effectif": "01", 
        "libelle_classe_effectif": "1 ou 2 salari\u00e9s", 
        "montant": "202900331.01", 
        "nombre": "55124", 
        "nombre_siren": "13486"
      }, 
      {
        "classe_effectif": "02", 
        "libelle_classe_effectif": "3 \u00e0 5 salari\u00e9s", 
        "montant": "101052800.82", 
        "nombre": "19972", 
        "nombre_siren": "4914"
      }, 
      {
        "classe_effectif": "03", 
        "libelle_classe_effectif": "6 \u00e0 9 salari\u00e9s", 
        "montant": "44529251.82", 
        "nombre": "6467", 
        "nombre_siren": "1591"
      }, 
      {
        "classe_effectif": "NN", 
        "libelle_classe_effectif": "Etablissement non employeur", 
        "montant": "36316141.05", 
        "nombre": "19233", 
        "nombre_siren": "5023"
      }, 
      {
        "classe_effectif": "Autres", 
        "libelle_classe_effectif": "Autres Classes d'Effectifs", 
        "montant": "70649975.44", 
        "nombre": "3913", 
        "nombre_siren": "1000"
      }
    ], 
    "kpi_top_10_naf": [
      {
        "libelle_section_naf": "H\u00e9bergement et restauration", 
        "montant": "299130640.47", 
        "nombre": "57654", 
        "nombre_siren": "8103", 
        "section_naf": "I"
      }, 
      {
        "libelle_section_naf": "Commerce", 
        "montant": "100699624.00", 
        "nombre": "43116", 
        "nombre_siren": "12132", 
        "section_naf": "G"
      }, 
      {
        "libelle_section_naf": "Autres activit\u00e9s de services", 
        "montant": "50301869.00", 
        "nombre": "27259", 
        "nombre_siren": "7267", 
        "section_naf": "S"
      }, 
      {
        "libelle_section_naf": "Arts, spectacles et activit\u00e9s r\u00e9cr\u00e9atives", 
        "montant": "56311960.33", 
        "nombre": "20458", 
        "nombre_siren": "3205", 
        "section_naf": "R"
      }, 
      {
        "libelle_section_naf": "Construction", 
        "montant": "30625001.00", 
        "nombre": "19926", 
        "nombre_siren": "8004", 
        "section_naf": "F"
      }, 
      {
        "libelle_section_naf": "Activit\u00e9s sp\u00e9cialis\u00e9es, scientifiques et techniques", 
        "montant": "49932088.39", 
        "nombre": "18178", 
        "nombre_siren": "4826", 
        "section_naf": "M"
      }, 
      {
        "libelle_section_naf": "Enseignement", 
        "montant": "22451789.00", 
        "nombre": "13640", 
        "nombre_siren": "2752", 
        "section_naf": "P"
      }, 
      {
        "libelle_section_naf": "Sant\u00e9 humaine et action sociale", 
        "montant": "16675068.00", 
        "nombre": "12569", 
        "nombre_siren": "5276", 
        "section_naf": "Q"
      }, 
      {
        "libelle_section_naf": "Industrie manufacturi\u00e8re", 
        "montant": "18559380.77", 
        "nombre": "10361", 
        "nombre_siren": "3207", 
        "section_naf": "C"
      }, 
      {
        "libelle_section_naf": "Activit\u00e9s de services administratifs et de soutien", 
        "montant": "24067024.00", 
        "nombre": "8894", 
        "nombre_siren": "2263", 
        "section_naf": "N"
      }, 
      {
        "libelle_section_naf": "Autres sections NAF", 
        "montant": "59105125.69", 
        "nombre": "25764", 
        "nombre_siren": "7567", 
        "section_naf": "Autres"
      }
    ], 
    "libelle": "Bourgogne-Franche-Comt\u00e9", 
    "montant": "727859570.65", 
    "nombre": "257819", 
    "nombre_siren": "64475", 
    "reg": "27"
  }, 
  {
    "kpi_categorie_juridique": [
      {
        "code_cat_juridique": "54", 
        "libelle_cat_juridique": "Soci\u00e9t\u00e9 \u00e0 responsabilit\u00e9 limit\u00e9e (SARL)", 
        "montant": "335701970.84", 
        "nombre": "75721", 
        "nombre_siren": "18150"
      }, 
      {
        "code_cat_juridique": "10", 
        "libelle_cat_juridique": "Entrepreneur individuel", 
        "montant": "294588473.70", 
        "nombre": "163202", 
        "nombre_siren": "42282"
      }, 
      {
        "code_cat_juridique": "57", 
        "libelle_cat_juridique": "Soci\u00e9t\u00e9 par actions simplifi\u00e9e", 
        "montant": "153873849.70", 
        "nombre": "31518", 
        "nombre_siren": "7043"
      }, 
      {
        "code_cat_juridique": "Autres", 
        "libelle_cat_juridique": "Autres Cat\u00e9gories Juridiques", 
        "montant": "45205944.00", 
        "nombre": "10478", 
        "nombre_siren": "2424"
      }
    ], 
    "kpi_classe_effectif": [
      {
        "classe_effectif": "00", 
        "libelle_classe_effectif": "0 salari\u00e9", 
        "montant": "69283017.23", 
        "nombre": "22836", 
        "nombre_siren": "5201"
      }, 
      {
        "classe_effectif": "01", 
        "libelle_classe_effectif": "1 ou 2 salari\u00e9s", 
        "montant": "224176782.25", 
        "nombre": "61149", 
        "nombre_siren": "15024"
      }, 
      {
        "classe_effectif": "02", 
        "libelle_classe_effectif": "3 \u00e0 5 salari\u00e9s", 
        "montant": "119639154.72", 
        "nombre": "23559", 
        "nombre_siren": "5742"
      }, 
      {
        "classe_effectif": "03", 
        "libelle_classe_effectif": "6 \u00e0 9 salari\u00e9s", 
        "montant": "57928339.37", 
        "nombre": "8233", 
        "nombre_siren": "2000"
      }, 
      {
        "classe_effectif": "NN", 
        "libelle_classe_effectif": "Etablissement non employeur", 
        "montant": "32475648.00", 
        "nombre": "17546", 
        "nombre_siren": "4613"
      }, 
      {
        "classe_effectif": "Autres", 
        "libelle_classe_effectif": "Autres Classes d'Effectifs", 
        "montant": "91181782.81", 
        "nombre": "4775", 
        "nombre_siren": "1168"
      }
    ], 
    "kpi_top_10_naf": [
      {
        "libelle_section_naf": "H\u00e9bergement et restauration", 
        "montant": "349537022.37", 
        "nombre": "63401", 
        "nombre_siren": "9286", 
        "section_naf": "I"
      }, 
      {
        "libelle_section_naf": "Commerce", 
        "montant": "111668360.00", 
        "nombre": "47737", 
        "nombre_siren": "13270", 
        "section_naf": "G"
      }, 
      {
        "libelle_section_naf": "Autres activit\u00e9s de services", 
        "montant": "59152473.35", 
        "nombre": "32776", 
        "nombre_siren": "8675", 
        "section_naf": "S"
      }, 
      {
        "libelle_section_naf": "Activit\u00e9s sp\u00e9cialis\u00e9es, scientifiques et techniques", 
        "montant": "64103071.77", 
        "nombre": "22712", 
        "nombre_siren": "5860", 
        "section_naf": "M"
      }, 
      {
        "libelle_section_naf": "Arts, spectacles et activit\u00e9s r\u00e9cr\u00e9atives", 
        "montant": "67217342.24", 
        "nombre": "22260", 
        "nombre_siren": "3656", 
        "section_naf": "R"
      }, 
      {
        "libelle_section_naf": "Construction", 
        "montant": "32281571.00", 
        "nombre": "20425", 
        "nombre_siren": "8379", 
        "section_naf": "F"
      }, 
      {
        "libelle_section_naf": "Enseignement", 
        "montant": "21790350.00", 
        "nombre": "12759", 
        "nombre_siren": "2685", 
        "section_naf": "P"
      }, 
      {
        "libelle_section_naf": "Sant\u00e9 humaine et action sociale", 
        "montant": "16585874.00", 
        "nombre": "12659", 
        "nombre_siren": "5410", 
        "section_naf": "Q"
      }, 
      {
        "libelle_section_naf": "Activit\u00e9s de services administratifs et de soutien", 
        "montant": "29107621.00", 
        "nombre": "10638", 
        "nombre_siren": "2583", 
        "section_naf": "N"
      }, 
      {
        "libelle_section_naf": "Industrie manufacturi\u00e8re", 
        "montant": "17777002.00", 
        "nombre": "9747", 
        "nombre_siren": "2985", 
        "section_naf": "C"
      }, 
      {
        "libelle_section_naf": "Autres sections NAF", 
        "montant": "63722180.51", 
        "nombre": "28981", 
        "nombre_siren": "7630", 
        "section_naf": "Autres"
      }
    ], 
    "libelle": "Normandie", 
    "montant": "832942868.24", 
    "nombre": "284095", 
    "nombre_siren": "70269", 
    "reg": "28"
  }, 
  {
    "kpi_categorie_juridique": [
      {
        "code_cat_juridique": "54", 
        "libelle_cat_juridique": "Soci\u00e9t\u00e9 \u00e0 responsabilit\u00e9 limit\u00e9e (SARL)", 
        "montant": "480806597.85", 
        "nombre": "114520", 
        "nombre_siren": "27553"
      }, 
      {
        "code_cat_juridique": "10", 
        "libelle_cat_juridique": "Entrepreneur individuel", 
        "montant": "453331424.54", 
        "nombre": "266435", 
        "nombre_siren": "67398"
      }, 
      {
        "code_cat_juridique": "57", 
        "libelle_cat_juridique": "Soci\u00e9t\u00e9 par actions simplifi\u00e9e", 
        "montant": "276279019.42", 
        "nombre": "63620", 
        "nombre_siren": "14149"
      }, 
      {
        "code_cat_juridique": "Autres", 
        "libelle_cat_juridique": "Autres Cat\u00e9gories Juridiques", 
        "montant": "61437841.05", 
        "nombre": "13782", 
        "nombre_siren": "3275"
      }
    ], 
    "kpi_classe_effectif": [
      {
        "classe_effectif": "00", 
        "libelle_classe_effectif": "0 salari\u00e9", 
        "montant": "83920753.18", 
        "nombre": "31440", 
        "nombre_siren": "7409"
      }, 
      {
        "classe_effectif": "01", 
        "libelle_classe_effectif": "1 ou 2 salari\u00e9s", 
        "montant": "324515920.93", 
        "nombre": "93902", 
        "nombre_siren": "22593"
      }, 
      {
        "classe_effectif": "02", 
        "libelle_classe_effectif": "3 \u00e0 5 salari\u00e9s", 
        "montant": "184893062.44", 
        "nombre": "37300", 
        "nombre_siren": "8966"
      }, 
      {
        "classe_effectif": "03", 
        "libelle_classe_effectif": "6 \u00e0 9 salari\u00e9s", 
        "montant": "82120454.11", 
        "nombre": "12823", 
        "nombre_siren": "3158"
      }, 
      {
        "classe_effectif": "NN", 
        "libelle_classe_effectif": "Etablissement non employeur", 
        "montant": "52076480.65", 
        "nombre": "28182", 
        "nombre_siren": "7168"
      }, 
      {
        "classe_effectif": "Autres", 
        "libelle_classe_effectif": "Autres Classes d'Effectifs", 
        "montant": "150971752.13", 
        "nombre": "7818", 
        "nombre_siren": "2001"
      }
    ], 
    "kpi_top_10_naf": [
      {
        "libelle_section_naf": "H\u00e9bergement et restauration", 
        "montant": "497085728.57", 
        "nombre": "92754", 
        "nombre_siren": "13316", 
        "section_naf": "I"
      }, 
      {
        "libelle_section_naf": "Commerce", 
        "montant": "176440650.00", 
        "nombre": "77737", 
        "nombre_siren": "20817", 
        "section_naf": "G"
      }, 
      {
        "libelle_section_naf": "Autres activit\u00e9s de services", 
        "montant": "89443421.06", 
        "nombre": "52881", 
        "nombre_siren": "13937", 
        "section_naf": "S"
      }, 
      {
        "libelle_section_naf": "Activit\u00e9s sp\u00e9cialis\u00e9es, scientifiques et techniques", 
        "montant": "97762570.92", 
        "nombre": "38493", 
        "nombre_siren": "9849", 
        "section_naf": "M"
      }, 
      {
        "libelle_section_naf": "Construction", 
        "montant": "53076995.00", 
        "nombre": "34072", 
        "nombre_siren": "12978", 
        "section_naf": "F"
      }, 
      {
        "libelle_section_naf": "Arts, spectacles et activit\u00e9s r\u00e9cr\u00e9atives", 
        "montant": "97927073.01", 
        "nombre": "33869", 
        "nombre_siren": "5206", 
        "section_naf": "R"
      }, 
      {
        "libelle_section_naf": "Transports et entreposage", 
        "montant": "61281337.78", 
        "nombre": "30040", 
        "nombre_siren": "5191", 
        "section_naf": "H"
      }, 
      {
        "libelle_section_naf": "Sant\u00e9 humaine et action sociale", 
        "montant": "35305346.00", 
        "nombre": "25882", 
        "nombre_siren": "11363", 
        "section_naf": "Q"
      }, 
      {
        "libelle_section_naf": "Enseignement", 
        "montant": "31741152.82", 
        "nombre": "18631", 
        "nombre_siren": "4076", 
        "section_naf": "P"
      }, 
      {
        "libelle_section_naf": "Activit\u00e9s de services administratifs et de soutien", 
        "montant": "47988600.08", 
        "nombre": "17031", 
        "nombre_siren": "4207", 
        "section_naf": "N"
      }, 
      {
        "libelle_section_naf": "Autres sections NAF", 
        "montant": "89802375.62", 
        "nombre": "42278", 
        "nombre_siren": "12205", 
        "section_naf": "Autres"
      }
    ], 
    "libelle": "Hauts-de-France", 
    "montant": "1277855250.86", 
    "nombre": "463668", 
    "nombre_siren": "112927", 
    "reg": "32"
  }, 
  {
    "kpi_categorie_juridique": [
      {
        "code_cat_juridique": "54", 
        "libelle_cat_juridique": "Soci\u00e9t\u00e9 \u00e0 responsabilit\u00e9 limit\u00e9e (SARL)", 
        "montant": "601310802.68", 
        "nombre": "140349", 
        "nombre_siren": "34368"
      }, 
      {
        "code_cat_juridique": "10", 
        "libelle_cat_juridique": "Entrepreneur individuel", 
        "montant": "500929187.67", 
        "nombre": "273361", 
        "nombre_siren": "71034"
      }, 
      {
        "code_cat_juridique": "57", 
        "libelle_cat_juridique": "Soci\u00e9t\u00e9 par actions simplifi\u00e9e", 
        "montant": "312222220.56", 
        "nombre": "68663", 
        "nombre_siren": "16306"
      }, 
      {
        "code_cat_juridique": "Autres", 
        "libelle_cat_juridique": "Autres Cat\u00e9gories Juridiques", 
        "montant": "157924540.00", 
        "nombre": "29790", 
        "nombre_siren": "9095"
      }
    ], 
    "kpi_classe_effectif": [
      {
        "classe_effectif": "00", 
        "libelle_classe_effectif": "0 salari\u00e9", 
        "montant": "110984909.89", 
        "nombre": "37222", 
        "nombre_siren": "9345"
      }, 
      {
        "classe_effectif": "01", 
        "libelle_classe_effectif": "1 ou 2 salari\u00e9s", 
        "montant": "411308159.18", 
        "nombre": "111815", 
        "nombre_siren": "28493"
      }, 
      {
        "classe_effectif": "02", 
        "libelle_classe_effectif": "3 \u00e0 5 salari\u00e9s", 
        "montant": "232627245.68", 
        "nombre": "46043", 
        "nombre_siren": "11540"
      }, 
      {
        "classe_effectif": "03", 
        "libelle_classe_effectif": "6 \u00e0 9 salari\u00e9s", 
        "montant": "116997300.02", 
        "nombre": "16869", 
        "nombre_siren": "4039"
      }, 
      {
        "classe_effectif": "NN", 
        "libelle_classe_effectif": "Etablissement non employeur", 
        "montant": "97151420.00", 
        "nombre": "40657", 
        "nombre_siren": "11309"
      }, 
      {
        "classe_effectif": "Autres", 
        "libelle_classe_effectif": "Autres Classes d'Effectifs", 
        "montant": "188720039.76", 
        "nombre": "9969", 
        "nombre_siren": "2400"
      }
    ], 
    "kpi_top_10_naf": [
      {
        "libelle_section_naf": "H\u00e9bergement et restauration", 
        "montant": "580263320.20", 
        "nombre": "99351", 
        "nombre_siren": "13895", 
        "section_naf": "I"
      }, 
      {
        "libelle_section_naf": "Commerce", 
        "montant": "198519531.43", 
        "nombre": "81204", 
        "nombre_siren": "22378", 
        "section_naf": "G"
      }, 
      {
        "libelle_section_naf": "Autres activit\u00e9s de services", 
        "montant": "102433569.53", 
        "nombre": "55637", 
        "nombre_siren": "14700", 
        "section_naf": "S"
      }, 
      {
        "libelle_section_naf": "Construction", 
        "montant": "65000357.00", 
        "nombre": "41772", 
        "nombre_siren": "15807", 
        "section_naf": "F"
      }, 
      {
        "libelle_section_naf": "Activit\u00e9s sp\u00e9cialis\u00e9es, scientifiques et techniques", 
        "montant": "97645368.59", 
        "nombre": "39633", 
        "nombre_siren": "10460", 
        "section_naf": "M"
      }, 
      {
        "libelle_section_naf": "Agriculture, sylviculture et p\u00eache", 
        "montant": "174195904.00", 
        "nombre": "36207", 
        "nombre_siren": "12712", 
        "section_naf": "A"
      }, 
      {
        "libelle_section_naf": "Arts, spectacles et activit\u00e9s r\u00e9cr\u00e9atives", 
        "montant": "98411631.13", 
        "nombre": "34634", 
        "nombre_siren": "5364", 
        "section_naf": "R"
      }, 
      {
        "libelle_section_naf": "Sant\u00e9 humaine et action sociale", 
        "montant": "35019790.00", 
        "nombre": "25711", 
        "nombre_siren": "11116", 
        "section_naf": "Q"
      }, 
      {
        "libelle_section_naf": "Enseignement", 
        "montant": "39144282.00", 
        "nombre": "22300", 
        "nombre_siren": "4697", 
        "section_naf": "P"
      }, 
      {
        "libelle_section_naf": "Industrie manufacturi\u00e8re", 
        "montant": "46089342.25", 
        "nombre": "19078", 
        "nombre_siren": "5674", 
        "section_naf": "C"
      }, 
      {
        "libelle_section_naf": "Autres sections NAF", 
        "montant": "140331724.78", 
        "nombre": "60899", 
        "nombre_siren": "14706", 
        "section_naf": "Autres"
      }
    ], 
    "libelle": "Grand Est", 
    "montant": "1577054820.91", 
    "nombre": "516426", 
    "nombre_siren": "131282", 
    "reg": "44"
  }, 
  {
    "kpi_categorie_juridique": [
      {
        "code_cat_juridique": "54", 
        "libelle_cat_juridique": "Soci\u00e9t\u00e9 \u00e0 responsabilit\u00e9 limit\u00e9e (SARL)", 
        "montant": "462880868.82", 
        "nombre": "106939", 
        "nombre_siren": "26913"
      }, 
      {
        "code_cat_juridique": "10", 
        "libelle_cat_juridique": "Entrepreneur individuel", 
        "montant": "330186297.00", 
        "nombre": "192694", 
        "nombre_siren": "51981"
      }, 
      {
        "code_cat_juridique": "57", 
        "libelle_cat_juridique": "Soci\u00e9t\u00e9 par actions simplifi\u00e9e", 
        "montant": "153854208.63", 
        "nombre": "30411", 
        "nombre_siren": "7041"
      }, 
      {
        "code_cat_juridique": "Autres", 
        "libelle_cat_juridique": "Autres Cat\u00e9gories Juridiques", 
        "montant": "57287465.00", 
        "nombre": "13483", 
        "nombre_siren": "3308"
      }
    ], 
    "kpi_classe_effectif": [
      {
        "classe_effectif": "00", 
        "libelle_classe_effectif": "0 salari\u00e9", 
        "montant": "85775684.81", 
        "nombre": "27634", 
        "nombre_siren": "6446"
      }, 
      {
        "classe_effectif": "01", 
        "libelle_classe_effectif": "1 ou 2 salari\u00e9s", 
        "montant": "254935280.50", 
        "nombre": "67363", 
        "nombre_siren": "16976"
      }, 
      {
        "classe_effectif": "02", 
        "libelle_classe_effectif": "3 \u00e0 5 salari\u00e9s", 
        "montant": "142107012.83", 
        "nombre": "27575", 
        "nombre_siren": "6996"
      }, 
      {
        "classe_effectif": "03", 
        "libelle_classe_effectif": "6 \u00e0 9 salari\u00e9s", 
        "montant": "63895277.31", 
        "nombre": "8913", 
        "nombre_siren": "2375"
      }, 
      {
        "classe_effectif": "NN", 
        "libelle_classe_effectif": "Etablissement non employeur", 
        "montant": "34961162.00", 
        "nombre": "18937", 
        "nombre_siren": "5187"
      }, 
      {
        "classe_effectif": "Autres", 
        "libelle_classe_effectif": "Autres Classes d'Effectifs", 
        "montant": "107397212.72", 
        "nombre": "5390", 
        "nombre_siren": "1447"
      }
    ], 
    "kpi_top_10_naf": [
      {
        "libelle_section_naf": "H\u00e9bergement et restauration", 
        "montant": "381255889.68", 
        "nombre": "67612", 
        "nombre_siren": "9823", 
        "section_naf": "I"
      }, 
      {
        "libelle_section_naf": "Commerce", 
        "montant": "123756050.00", 
        "nombre": "50693", 
        "nombre_siren": "14369", 
        "section_naf": "G"
      }, 
      {
        "libelle_section_naf": "Autres activit\u00e9s de services", 
        "montant": "70170451.00", 
        "nombre": "37186", 
        "nombre_siren": "10223", 
        "section_naf": "S"
      }, 
      {
        "libelle_section_naf": "Activit\u00e9s sp\u00e9cialis\u00e9es, scientifiques et techniques", 
        "montant": "98360987.55", 
        "nombre": "34635", 
        "nombre_siren": "9179", 
        "section_naf": "M"
      }, 
      {
        "libelle_section_naf": "Arts, spectacles et activit\u00e9s r\u00e9cr\u00e9atives", 
        "montant": "86995060.22", 
        "nombre": "30089", 
        "nombre_siren": "5091", 
        "section_naf": "R"
      }, 
      {
        "libelle_section_naf": "Construction", 
        "montant": "35347460.00", 
        "nombre": "22764", 
        "nombre_siren": "10087", 
        "section_naf": "F"
      }, 
      {
        "libelle_section_naf": "Sant\u00e9 humaine et action sociale", 
        "montant": "29788055.00", 
        "nombre": "22677", 
        "nombre_siren": "9588", 
        "section_naf": "Q"
      }, 
      {
        "libelle_section_naf": "Enseignement", 
        "montant": "29356306.00", 
        "nombre": "16324", 
        "nombre_siren": "3572", 
        "section_naf": "P"
      }, 
      {
        "libelle_section_naf": "Industrie manufacturi\u00e8re", 
        "montant": "23128669.00", 
        "nombre": "13056", 
        "nombre_siren": "4043", 
        "section_naf": "C"
      }, 
      {
        "libelle_section_naf": "Transports et entreposage", 
        "montant": "30584818.00", 
        "nombre": "12843", 
        "nombre_siren": "2457", 
        "section_naf": "H"
      }, 
      {
        "libelle_section_naf": "Autres sections NAF", 
        "montant": "101143963.00", 
        "nombre": "40734", 
        "nombre_siren": "11564", 
        "section_naf": "Autres"
      }
    ], 
    "libelle": "Pays de la Loire", 
    "montant": "1009887709.45", 
    "nombre": "348613", 
    "nombre_siren": "89816", 
    "reg": "52"
  }, 
  {
    "kpi_categorie_juridique": [
      {
        "code_cat_juridique": "54", 
        "libelle_cat_juridique": "Soci\u00e9t\u00e9 \u00e0 responsabilit\u00e9 limit\u00e9e (SARL)", 
        "montant": "459504638.83", 
        "nombre": "100520", 
        "nombre_siren": "24009"
      }, 
      {
        "code_cat_juridique": "10", 
        "libelle_cat_juridique": "Entrepreneur individuel", 
        "montant": "322804053.84", 
        "nombre": "176580", 
        "nombre_siren": "47799"
      }, 
      {
        "code_cat_juridique": "57", 
        "libelle_cat_juridique": "Soci\u00e9t\u00e9 par actions simplifi\u00e9e", 
        "montant": "127002530.62", 
        "nombre": "22901", 
        "nombre_siren": "5404"
      }, 
      {
        "code_cat_juridique": "Autres", 
        "libelle_cat_juridique": "Autres Cat\u00e9gories Juridiques", 
        "montant": "61549388.30", 
        "nombre": "13434", 
        "nombre_siren": "3007"
      }
    ], 
    "kpi_classe_effectif": [
      {
        "classe_effectif": "00", 
        "libelle_classe_effectif": "0 salari\u00e9", 
        "montant": "97199861.30", 
        "nombre": "28812", 
        "nombre_siren": "6452"
      }, 
      {
        "classe_effectif": "01", 
        "libelle_classe_effectif": "1 ou 2 salari\u00e9s", 
        "montant": "273440874.74", 
        "nombre": "68903", 
        "nombre_siren": "16368"
      }, 
      {
        "classe_effectif": "02", 
        "libelle_classe_effectif": "3 \u00e0 5 salari\u00e9s", 
        "montant": "140739234.56", 
        "nombre": "26242", 
        "nombre_siren": "6403"
      }, 
      {
        "classe_effectif": "03", 
        "libelle_classe_effectif": "6 \u00e0 9 salari\u00e9s", 
        "montant": "65122747.45", 
        "nombre": "8750", 
        "nombre_siren": "2188"
      }, 
      {
        "classe_effectif": "NN", 
        "libelle_classe_effectif": "Etablissement non employeur", 
        "montant": "40136103.00", 
        "nombre": "21028", 
        "nombre_siren": "5575"
      }, 
      {
        "classe_effectif": "Autres", 
        "libelle_classe_effectif": "Autres Classes d'Effectifs", 
        "montant": "98006815.63", 
        "nombre": "5021", 
        "nombre_siren": "1307"
      }
    ], 
    "kpi_top_10_naf": [
      {
        "libelle_section_naf": "H\u00e9bergement et restauration", 
        "montant": "445910164.93", 
        "nombre": "78337", 
        "nombre_siren": "11217", 
        "section_naf": "I"
      }, 
      {
        "libelle_section_naf": "Commerce", 
        "montant": "112911042.00", 
        "nombre": "45534", 
        "nombre_siren": "13092", 
        "section_naf": "G"
      }, 
      {
        "libelle_section_naf": "Autres activit\u00e9s de services", 
        "montant": "58470602.78", 
        "nombre": "30659", 
        "nombre_siren": "8487", 
        "section_naf": "S"
      }, 
      {
        "libelle_section_naf": "Activit\u00e9s sp\u00e9cialis\u00e9es, scientifiques et techniques", 
        "montant": "78908850.79", 
        "nombre": "27293", 
        "nombre_siren": "7351", 
        "section_naf": "M"
      }, 
      {
        "libelle_section_naf": "Arts, spectacles et activit\u00e9s r\u00e9cr\u00e9atives", 
        "montant": "71670945.57", 
        "nombre": "25029", 
        "nombre_siren": "4338", 
        "section_naf": "R"
      }, 
      {
        "libelle_section_naf": "Sant\u00e9 humaine et action sociale", 
        "montant": "27492352.00", 
        "nombre": "20394", 
        "nombre_siren": "8861", 
        "section_naf": "Q"
      }, 
      {
        "libelle_section_naf": "Construction", 
        "montant": "30772798.00", 
        "nombre": "20274", 
        "nombre_siren": "9039", 
        "section_naf": "F"
      }, 
      {
        "libelle_section_naf": "Enseignement", 
        "montant": "26384943.00", 
        "nombre": "14721", 
        "nombre_siren": "3117", 
        "section_naf": "P"
      }, 
      {
        "libelle_section_naf": "Industrie manufacturi\u00e8re", 
        "montant": "24198729.00", 
        "nombre": "13943", 
        "nombre_siren": "4142", 
        "section_naf": "C"
      }, 
      {
        "libelle_section_naf": "Activit\u00e9s de services administratifs et de soutien", 
        "montant": "31721371.52", 
        "nombre": "10791", 
        "nombre_siren": "2911", 
        "section_naf": "N"
      }, 
      {
        "libelle_section_naf": "Autres sections NAF", 
        "montant": "66974885.00", 
        "nombre": "30458", 
        "nombre_siren": "8302", 
        "section_naf": "Autres"
      }
    ], 
    "libelle": "Bretagne", 
    "montant": "975416684.59", 
    "nombre": "317433", 
    "nombre_siren": "80707", 
    "reg": "53"
  }, 
  {
    "kpi_categorie_juridique": [
      {
        "code_cat_juridique": "54", 
        "libelle_cat_juridique": "Soci\u00e9t\u00e9 \u00e0 responsabilit\u00e9 limit\u00e9e (SARL)", 
        "montant": "803356184.05", 
        "nombre": "187003", 
        "nombre_siren": "45817"
      }, 
      {
        "code_cat_juridique": "10", 
        "libelle_cat_juridique": "Entrepreneur individuel", 
        "montant": "718986295.96", 
        "nombre": "431995", 
        "nombre_siren": "114400"
      }, 
      {
        "code_cat_juridique": "57", 
        "libelle_cat_juridique": "Soci\u00e9t\u00e9 par actions simplifi\u00e9e", 
        "montant": "358569728.51", 
        "nombre": "78172", 
        "nombre_siren": "17937"
      }, 
      {
        "code_cat_juridique": "Autres", 
        "libelle_cat_juridique": "Autres Cat\u00e9gories Juridiques", 
        "montant": "128738398.85", 
        "nombre": "29491", 
        "nombre_siren": "7868"
      }
    ], 
    "kpi_classe_effectif": [
      {
        "classe_effectif": "00", 
        "libelle_classe_effectif": "0 salari\u00e9", 
        "montant": "203507353.36", 
        "nombre": "64723", 
        "nombre_siren": "14839"
      }, 
      {
        "classe_effectif": "01", 
        "libelle_classe_effectif": "1 ou 2 salari\u00e9s", 
        "montant": "487542966.03", 
        "nombre": "135713", 
        "nombre_siren": "34649"
      }, 
      {
        "classe_effectif": "02", 
        "libelle_classe_effectif": "3 \u00e0 5 salari\u00e9s", 
        "montant": "250340928.80", 
        "nombre": "50018", 
        "nombre_siren": "12816"
      }, 
      {
        "classe_effectif": "03", 
        "libelle_classe_effectif": "6 \u00e0 9 salari\u00e9s", 
        "montant": "123634372.39", 
        "nombre": "17867", 
        "nombre_siren": "4505"
      }, 
      {
        "classe_effectif": "NN", 
        "libelle_classe_effectif": "Etablissement non employeur", 
        "montant": "86922431.00", 
        "nombre": "46641", 
        "nombre_siren": "12955"
      }, 
      {
        "classe_effectif": "Autres", 
        "libelle_classe_effectif": "Autres Classes d'Effectifs", 
        "montant": "206037375.48", 
        "nombre": "10547", 
        "nombre_siren": "2681"
      }
    ], 
    "kpi_top_10_naf": [
      {
        "libelle_section_naf": "H\u00e9bergement et restauration", 
        "montant": "736991257.35", 
        "nombre": "136949", 
        "nombre_siren": "20021", 
        "section_naf": "I"
      }, 
      {
        "libelle_section_naf": "Commerce", 
        "montant": "272402310.30", 
        "nombre": "116125", 
        "nombre_siren": "31695", 
        "section_naf": "G"
      }, 
      {
        "libelle_section_naf": "Autres activit\u00e9s de services", 
        "montant": "126911135.71", 
        "nombre": "72859", 
        "nombre_siren": "19850", 
        "section_naf": "S"
      }, 
      {
        "libelle_section_naf": "Activit\u00e9s sp\u00e9cialis\u00e9es, scientifiques et techniques", 
        "montant": "165246178.61", 
        "nombre": "64224", 
        "nombre_siren": "16917", 
        "section_naf": "M"
      }, 
      {
        "libelle_section_naf": "Construction", 
        "montant": "90829780.00", 
        "nombre": "58487", 
        "nombre_siren": "23829", 
        "section_naf": "F"
      }, 
      {
        "libelle_section_naf": "Arts, spectacles et activit\u00e9s r\u00e9cr\u00e9atives", 
        "montant": "148280711.11", 
        "nombre": "54100", 
        "nombre_siren": "8877", 
        "section_naf": "R"
      }, 
      {
        "libelle_section_naf": "Sant\u00e9 humaine et action sociale", 
        "montant": "54528802.00", 
        "nombre": "41158", 
        "nombre_siren": "17082", 
        "section_naf": "Q"
      }, 
      {
        "libelle_section_naf": "Enseignement", 
        "montant": "64087893.00", 
        "nombre": "38612", 
        "nombre_siren": "7701", 
        "section_naf": "P"
      }, 
      {
        "libelle_section_naf": "Activit\u00e9s de services administratifs et de soutien", 
        "montant": "79024813.00", 
        "nombre": "31710", 
        "nombre_siren": "8031", 
        "section_naf": "N"
      }, 
      {
        "libelle_section_naf": "Industrie manufacturi\u00e8re", 
        "montant": "51636068.50", 
        "nombre": "29674", 
        "nombre_siren": "8710", 
        "section_naf": "C"
      }, 
      {
        "libelle_section_naf": "Autres sections NAF", 
        "montant": "228399770.79", 
        "nombre": "90761", 
        "nombre_siren": "24598", 
        "section_naf": "Autres"
      }
    ], 
    "libelle": "Nouvelle-Aquitaine", 
    "montant": "2018338720.37", 
    "nombre": "734659", 
    "nombre_siren": "186861", 
    "reg": "75"
  }, 
  {
    "kpi_categorie_juridique": [
      {
        "code_cat_juridique": "54", 
        "libelle_cat_juridique": "Soci\u00e9t\u00e9 \u00e0 responsabilit\u00e9 limit\u00e9e (SARL)", 
        "montant": "880206020.14", 
        "nombre": "211819", 
        "nombre_siren": "49249"
      }, 
      {
        "code_cat_juridique": "10", 
        "libelle_cat_juridique": "Entrepreneur individuel", 
        "montant": "802082432.57", 
        "nombre": "499025", 
        "nombre_siren": "126050"
      }, 
      {
        "code_cat_juridique": "57", 
        "libelle_cat_juridique": "Soci\u00e9t\u00e9 par actions simplifi\u00e9e", 
        "montant": "507425183.15", 
        "nombre": "122222", 
        "nombre_siren": "26654"
      }, 
      {
        "code_cat_juridique": "Autres", 
        "libelle_cat_juridique": "Autres Cat\u00e9gories Juridiques", 
        "montant": "138183970.19", 
        "nombre": "30454", 
        "nombre_siren": "7411"
      }
    ], 
    "kpi_classe_effectif": [
      {
        "classe_effectif": "00", 
        "libelle_classe_effectif": "0 salari\u00e9", 
        "montant": "250554177.56", 
        "nombre": "80150", 
        "nombre_siren": "17170"
      }, 
      {
        "classe_effectif": "01", 
        "libelle_classe_effectif": "1 ou 2 salari\u00e9s", 
        "montant": "574022727.86", 
        "nombre": "163614", 
        "nombre_siren": "38894"
      }, 
      {
        "classe_effectif": "02", 
        "libelle_classe_effectif": "3 \u00e0 5 salari\u00e9s", 
        "montant": "284972533.32", 
        "nombre": "56861", 
        "nombre_siren": "13712"
      }, 
      {
        "classe_effectif": "03", 
        "libelle_classe_effectif": "6 \u00e0 9 salari\u00e9s", 
        "montant": "128625773.76", 
        "nombre": "18882", 
        "nombre_siren": "4555"
      }, 
      {
        "classe_effectif": "NN", 
        "libelle_classe_effectif": "Etablissement non employeur", 
        "montant": "103367842.00", 
        "nombre": "58828", 
        "nombre_siren": "15323"
      }, 
      {
        "classe_effectif": "Autres", 
        "libelle_classe_effectif": "Autres Classes d'Effectifs", 
        "montant": "229404927.21", 
        "nombre": "10648", 
        "nombre_siren": "2699"
      }
    ], 
    "kpi_top_10_naf": [
      {
        "libelle_section_naf": "H\u00e9bergement et restauration", 
        "montant": "854571924.63", 
        "nombre": "165004", 
        "nombre_siren": "23125", 
        "section_naf": "I"
      }, 
      {
        "libelle_section_naf": "Commerce", 
        "montant": "316228962.95", 
        "nombre": "138712", 
        "nombre_siren": "35259", 
        "section_naf": "G"
      }, 
      {
        "libelle_section_naf": "Construction", 
        "montant": "125569286.07", 
        "nombre": "81962", 
        "nombre_siren": "29583", 
        "section_naf": "F"
      }, 
      {
        "libelle_section_naf": "Activit\u00e9s sp\u00e9cialis\u00e9es, scientifiques et techniques", 
        "montant": "202996668.86", 
        "nombre": "77530", 
        "nombre_siren": "19444", 
        "section_naf": "M"
      }, 
      {
        "libelle_section_naf": "Autres activit\u00e9s de services", 
        "montant": "129452205.37", 
        "nombre": "77133", 
        "nombre_siren": "20110", 
        "section_naf": "S"
      }, 
      {
        "libelle_section_naf": "Arts, spectacles et activit\u00e9s r\u00e9cr\u00e9atives", 
        "montant": "175269002.26", 
        "nombre": "64964", 
        "nombre_siren": "10142", 
        "section_naf": "R"
      }, 
      {
        "libelle_section_naf": "Enseignement", 
        "montant": "78398617.59", 
        "nombre": "49180", 
        "nombre_siren": "9793", 
        "section_naf": "P"
      }, 
      {
        "libelle_section_naf": "Sant\u00e9 humaine et action sociale", 
        "montant": "61300684.00", 
        "nombre": "45996", 
        "nombre_siren": "19293", 
        "section_naf": "Q"
      }, 
      {
        "libelle_section_naf": "Activit\u00e9s de services administratifs et de soutien", 
        "montant": "89637214.52", 
        "nombre": "35524", 
        "nombre_siren": "8853", 
        "section_naf": "N"
      }, 
      {
        "libelle_section_naf": "Industrie manufacturi\u00e8re", 
        "montant": "59052013.39", 
        "nombre": "33295", 
        "nombre_siren": "9418", 
        "section_naf": "C"
      }, 
      {
        "libelle_section_naf": "Autres sections NAF", 
        "montant": "247097968.41", 
        "nombre": "104686", 
        "nombre_siren": "25906", 
        "section_naf": "Autres"
      }
    ], 
    "libelle": "Occitanie", 
    "montant": "2339574548.05", 
    "nombre": "873986", 
    "nombre_siren": "210419", 
    "reg": "76"
  }, 
  {
    "kpi_categorie_juridique": [
      {
        "code_cat_juridique": "54", 
        "libelle_cat_juridique": "Soci\u00e9t\u00e9 \u00e0 responsabilit\u00e9 limit\u00e9e (SARL)", 
        "montant": "1224959707.95", 
        "nombre": "269067", 
        "nombre_siren": "63395"
      }, 
      {
        "code_cat_juridique": "10", 
        "libelle_cat_juridique": "Entrepreneur individuel", 
        "montant": "1114576188.43", 
        "nombre": "632260", 
        "nombre_siren": "154649"
      }, 
      {
        "code_cat_juridique": "57", 
        "libelle_cat_juridique": "Soci\u00e9t\u00e9 par actions simplifi\u00e9e", 
        "montant": "775557475.89", 
        "nombre": "144631", 
        "nombre_siren": "32520"
      }, 
      {
        "code_cat_juridique": "Autres", 
        "libelle_cat_juridique": "Autres Cat\u00e9gories Juridiques", 
        "montant": "339205891.91", 
        "nombre": "33754", 
        "nombre_siren": "8326"
      }
    ], 
    "kpi_classe_effectif": [
      {
        "classe_effectif": "00", 
        "libelle_classe_effectif": "0 salari\u00e9", 
        "montant": "238505969.19", 
        "nombre": "81037", 
        "nombre_siren": "18836"
      }, 
      {
        "classe_effectif": "01", 
        "libelle_classe_effectif": "1 ou 2 salari\u00e9s", 
        "montant": "738675014.88", 
        "nombre": "198373", 
        "nombre_siren": "47075"
      }, 
      {
        "classe_effectif": "02", 
        "libelle_classe_effectif": "3 \u00e0 5 salari\u00e9s", 
        "montant": "424018611.14", 
        "nombre": "78869", 
        "nombre_siren": "18493"
      }, 
      {
        "classe_effectif": "03", 
        "libelle_classe_effectif": "6 \u00e0 9 salari\u00e9s", 
        "montant": "227497804.22", 
        "nombre": "28605", 
        "nombre_siren": "6492"
      }, 
      {
        "classe_effectif": "NN", 
        "libelle_classe_effectif": "Etablissement non employeur", 
        "montant": "181295149.49", 
        "nombre": "87099", 
        "nombre_siren": "20698"
      }, 
      {
        "classe_effectif": "Autres", 
        "libelle_classe_effectif": "Autres Classes d'Effectifs", 
        "montant": "656202006.12", 
        "nombre": "18358", 
        "nombre_siren": "4548"
      }
    ], 
    "kpi_top_10_naf": [
      {
        "libelle_section_naf": "H\u00e9bergement et restauration", 
        "montant": "1197910238.85", 
        "nombre": "205375", 
        "nombre_siren": "29049", 
        "section_naf": "I"
      }, 
      {
        "libelle_section_naf": "Commerce", 
        "montant": "414832719.57", 
        "nombre": "148138", 
        "nombre_siren": "39483", 
        "section_naf": "G"
      }, 
      {
        "libelle_section_naf": "Enseignement", 
        "montant": "199377820.98", 
        "nombre": "103820", 
        "nombre_siren": "19365", 
        "section_naf": "P"
      }, 
      {
        "libelle_section_naf": "Activit\u00e9s sp\u00e9cialis\u00e9es, scientifiques et techniques", 
        "montant": "274548964.54", 
        "nombre": "96356", 
        "nombre_siren": "24823", 
        "section_naf": "M"
      }, 
      {
        "libelle_section_naf": "Autres activit\u00e9s de services", 
        "montant": "171040165.87", 
        "nombre": "91543", 
        "nombre_siren": "23982", 
        "section_naf": "S"
      }, 
      {
        "libelle_section_naf": "Construction", 
        "montant": "138949709.87", 
        "nombre": "86508", 
        "nombre_siren": "31997", 
        "section_naf": "F"
      }, 
      {
        "libelle_section_naf": "Arts, spectacles et activit\u00e9s r\u00e9cr\u00e9atives", 
        "montant": "231796695.17", 
        "nombre": "82346", 
        "nombre_siren": "13245", 
        "section_naf": "R"
      }, 
      {
        "libelle_section_naf": "Sant\u00e9 humaine et action sociale", 
        "montant": "78114941.60", 
        "nombre": "57681", 
        "nombre_siren": "23641", 
        "section_naf": "Q"
      }, 
      {
        "libelle_section_naf": "Transports et entreposage", 
        "montant": "372255955.41", 
        "nombre": "56586", 
        "nombre_siren": "9900", 
        "section_naf": "H"
      }, 
      {
        "libelle_section_naf": "Activit\u00e9s de services administratifs et de soutien", 
        "montant": "135644182.00", 
        "nombre": "45705", 
        "nombre_siren": "11149", 
        "section_naf": "N"
      }, 
      {
        "libelle_section_naf": "Autres sections NAF", 
        "montant": "258938010.32", 
        "nombre": "121755", 
        "nombre_siren": "34482", 
        "section_naf": "Autres"
      }
    ], 
    "libelle": "Auvergne-Rh\u00f4ne-Alpes", 
    "montant": "3473409404.18", 
    "nombre": "1095813", 
    "nombre_siren": "260425", 
    "reg": "84"
  }, 
  {
    "kpi_categorie_juridique": [
      {
        "code_cat_juridique": "54", 
        "libelle_cat_juridique": "Soci\u00e9t\u00e9 \u00e0 responsabilit\u00e9 limit\u00e9e (SARL)", 
        "montant": "976877316.75", 
        "nombre": "224304", 
        "nombre_siren": "49293"
      }, 
      {
        "code_cat_juridique": "10", 
        "libelle_cat_juridique": "Entrepreneur individuel", 
        "montant": "845296208.09", 
        "nombre": "510594", 
        "nombre_siren": "120235"
      }, 
      {
        "code_cat_juridique": "57", 
        "libelle_cat_juridique": "Soci\u00e9t\u00e9 par actions simplifi\u00e9e", 
        "montant": "720319024.52", 
        "nombre": "162312", 
        "nombre_siren": "33430"
      }, 
      {
        "code_cat_juridique": "Autres", 
        "libelle_cat_juridique": "Autres Cat\u00e9gories Juridiques", 
        "montant": "127003840.44", 
        "nombre": "24450", 
        "nombre_siren": "5482"
      }
    ], 
    "kpi_classe_effectif": [
      {
        "classe_effectif": "00", 
        "libelle_classe_effectif": "0 salari\u00e9", 
        "montant": "241247392.43", 
        "nombre": "78442", 
        "nombre_siren": "16699"
      }, 
      {
        "classe_effectif": "01", 
        "libelle_classe_effectif": "1 ou 2 salari\u00e9s", 
        "montant": "651596157.35", 
        "nombre": "182294", 
        "nombre_siren": "40623"
      }, 
      {
        "classe_effectif": "02", 
        "libelle_classe_effectif": "3 \u00e0 5 salari\u00e9s", 
        "montant": "331210745.09", 
        "nombre": "63048", 
        "nombre_siren": "13917"
      }, 
      {
        "classe_effectif": "03", 
        "libelle_classe_effectif": "6 \u00e0 9 salari\u00e9s", 
        "montant": "164937136.41", 
        "nombre": "21434", 
        "nombre_siren": "4636"
      }, 
      {
        "classe_effectif": "NN", 
        "libelle_classe_effectif": "Etablissement non employeur", 
        "montant": "103115593.22", 
        "nombre": "56357", 
        "nombre_siren": "13580"
      }, 
      {
        "classe_effectif": "Autres", 
        "libelle_classe_effectif": "Autres Classes d'Effectifs", 
        "montant": "322189812.61", 
        "nombre": "13306", 
        "nombre_siren": "3125"
      }
    ], 
    "kpi_top_10_naf": [
      {
        "libelle_section_naf": "H\u00e9bergement et restauration", 
        "montant": "954941187.56", 
        "nombre": "168181", 
        "nombre_siren": "23055", 
        "section_naf": "I"
      }, 
      {
        "libelle_section_naf": "Commerce", 
        "montant": "385756254.24", 
        "nombre": "155766", 
        "nombre_siren": "37176", 
        "section_naf": "G"
      }, 
      {
        "libelle_section_naf": "Activit\u00e9s sp\u00e9cialis\u00e9es, scientifiques et techniques", 
        "montant": "216014678.70", 
        "nombre": "84340", 
        "nombre_siren": "20846", 
        "section_naf": "M"
      }, 
      {
        "libelle_section_naf": "Autres activit\u00e9s de services", 
        "montant": "139860388.41", 
        "nombre": "79157", 
        "nombre_siren": "19700", 
        "section_naf": "S"
      }, 
      {
        "libelle_section_naf": "Construction", 
        "montant": "120142029.00", 
        "nombre": "75692", 
        "nombre_siren": "25957", 
        "section_naf": "F"
      }, 
      {
        "libelle_section_naf": "Arts, spectacles et activit\u00e9s r\u00e9cr\u00e9atives", 
        "montant": "178346751.05", 
        "nombre": "61630", 
        "nombre_siren": "9459", 
        "section_naf": "R"
      }, 
      {
        "libelle_section_naf": "Transports et entreposage", 
        "montant": "174097538.06", 
        "nombre": "59765", 
        "nombre_siren": "9179", 
        "section_naf": "H"
      }, 
      {
        "libelle_section_naf": "Enseignement", 
        "montant": "93898372.19", 
        "nombre": "54151", 
        "nombre_siren": "10170", 
        "section_naf": "P"
      }, 
      {
        "libelle_section_naf": "Activit\u00e9s de services administratifs et de soutien", 
        "montant": "135059609.89", 
        "nombre": "47017", 
        "nombre_siren": "10738", 
        "section_naf": "N"
      }, 
      {
        "libelle_section_naf": "Sant\u00e9 humaine et action sociale", 
        "montant": "56538810.00", 
        "nombre": "42571", 
        "nombre_siren": "17337", 
        "section_naf": "Q"
      }, 
      {
        "libelle_section_naf": "Autres sections NAF", 
        "montant": "224018741.70", 
        "nombre": "101535", 
        "nombre_siren": "26075", 
        "section_naf": "Autres"
      }
    ], 
    "libelle": "Provence-Alpes-C\u00f4te d'Azur", 
    "montant": "2678674360.80", 
    "nombre": "929805", 
    "nombre_siren": "209146", 
    "reg": "93"
  }, 
  {
    "kpi_categorie_juridique": [
      {
        "code_cat_juridique": "54", 
        "libelle_cat_juridique": "Soci\u00e9t\u00e9 \u00e0 responsabilit\u00e9 limit\u00e9e (SARL)", 
        "montant": "112256871.44", 
        "nombre": "20917", 
        "nombre_siren": "4221"
      }, 
      {
        "code_cat_juridique": "10", 
        "libelle_cat_juridique": "Entrepreneur individuel", 
        "montant": "80333727.37", 
        "nombre": "40563", 
        "nombre_siren": "9458"
      }, 
      {
        "code_cat_juridique": "57", 
        "libelle_cat_juridique": "Soci\u00e9t\u00e9 par actions simplifi\u00e9e", 
        "montant": "67068029.27", 
        "nombre": "13749", 
        "nombre_siren": "2841"
      }, 
      {
        "code_cat_juridique": "Autres", 
        "libelle_cat_juridique": "Autres Cat\u00e9gories Juridiques", 
        "montant": "8037776.93", 
        "nombre": "2317", 
        "nombre_siren": "499"
      }
    ], 
    "kpi_classe_effectif": [
      {
        "classe_effectif": "00", 
        "libelle_classe_effectif": "0 salari\u00e9", 
        "montant": "30233107.16", 
        "nombre": "8292", 
        "nombre_siren": "1527"
      }, 
      {
        "classe_effectif": "01", 
        "libelle_classe_effectif": "1 ou 2 salari\u00e9s", 
        "montant": "71404722.61", 
        "nombre": "18637", 
        "nombre_siren": "3817"
      }, 
      {
        "classe_effectif": "02", 
        "libelle_classe_effectif": "3 \u00e0 5 salari\u00e9s", 
        "montant": "46019563.02", 
        "nombre": "8493", 
        "nombre_siren": "1754"
      }, 
      {
        "classe_effectif": "03", 
        "libelle_classe_effectif": "6 \u00e0 9 salari\u00e9s", 
        "montant": "21382708.00", 
        "nombre": "2758", 
        "nombre_siren": "599"
      }, 
      {
        "classe_effectif": "NN", 
        "libelle_classe_effectif": "Etablissement non employeur", 
        "montant": "9291098.00", 
        "nombre": "5138", 
        "nombre_siren": "1235"
      }, 
      {
        "classe_effectif": "Autres", 
        "libelle_classe_effectif": "Autres Classes d'Effectifs", 
        "montant": "30934195.00", 
        "nombre": "1477", 
        "nombre_siren": "362"
      }
    ], 
    "kpi_top_10_naf": [
      {
        "libelle_section_naf": "H\u00e9bergement et restauration", 
        "montant": "113783222.57", 
        "nombre": "19864", 
        "nombre_siren": "2786", 
        "section_naf": "I"
      }, 
      {
        "libelle_section_naf": "Commerce", 
        "montant": "35640991.00", 
        "nombre": "11305", 
        "nombre_siren": "2601", 
        "section_naf": "G"
      }, 
      {
        "libelle_section_naf": "Activit\u00e9s sp\u00e9cialis\u00e9es, scientifiques et techniques", 
        "montant": "32663615.67", 
        "nombre": "8437", 
        "nombre_siren": "1828", 
        "section_naf": "M"
      }, 
      {
        "libelle_section_naf": "Construction", 
        "montant": "11609472.00", 
        "nombre": "7221", 
        "nombre_siren": "2448", 
        "section_naf": "F"
      }, 
      {
        "libelle_section_naf": "Autres activit\u00e9s de services", 
        "montant": "9366730.93", 
        "nombre": "5154", 
        "nombre_siren": "1277", 
        "section_naf": "S"
      }, 
      {
        "libelle_section_naf": "Agriculture, sylviculture et p\u00eache", 
        "montant": "8690674.00", 
        "nombre": "4495", 
        "nombre_siren": "1127", 
        "section_naf": "A"
      }, 
      {
        "libelle_section_naf": "Activit\u00e9s de services administratifs et de soutien", 
        "montant": "11669608.00", 
        "nombre": "4282", 
        "nombre_siren": "927", 
        "section_naf": "N"
      }, 
      {
        "libelle_section_naf": "Industrie manufacturi\u00e8re", 
        "montant": "7223522.00", 
        "nombre": "3720", 
        "nombre_siren": "904", 
        "section_naf": "C"
      }, 
      {
        "libelle_section_naf": "Arts, spectacles et activit\u00e9s r\u00e9cr\u00e9atives", 
        "montant": "12000078.84", 
        "nombre": "3604", 
        "nombre_siren": "546", 
        "section_naf": "R"
      }, 
      {
        "libelle_section_naf": "Activit\u00e9s immobili\u00e8res", 
        "montant": "9065249.00", 
        "nombre": "3300", 
        "nombre_siren": "696", 
        "section_naf": "L"
      }, 
      {
        "libelle_section_naf": "Autres sections NAF", 
        "montant": "18075196.00", 
        "nombre": "7726", 
        "nombre_siren": "2005", 
        "section_naf": "Autres"
      }
    ], 
    "libelle": "Corse", 
    "montant": "269788360.01", 
    "nombre": "79108", 
    "nombre_siren": "17104", 
    "reg": "94"
  }, 
  {
    "kpi_categorie_juridique": [
      {
        "code_cat_juridique": "Autres", 
        "libelle_cat_juridique": "Autres Cat\u00e9gories Juridiques", 
        "montant": "0", 
        "nombre": "0", 
        "nombre_siren": "0"
      }
    ], 
    "kpi_classe_effectif": [
      {
        "classe_effectif": "Autres", 
        "libelle_classe_effectif": "Autres Classes d'Effectifs", 
        "montant": "0", 
        "nombre": "0", 
        "nombre_siren": "0"
      }
    ], 
    "kpi_top_10_naf": [
      {
        "libelle_section_naf": "Autres sections NAF", 
        "montant": "0", 
        "nombre": "0", 
        "nombre_siren": "0", 
        "section_naf": "Autres"
      }
    ], 
    "libelle": "None", 
    "montant": "268682343.16", 
    "nombre": "144818", 
    "nombre_siren": "52218", 
    "reg": "None"
  }
]
